quickstart_django/__init__.py
quickstart_django/__main__.py
quickstart_django/quickstart_django.py
quickstart_django-1.1.dist-info/METADATA
quickstart_django-1.1.dist-info/WHEEL
quickstart_django-1.1.dist-info/licenses/LICENCE
quickstart_django-1.1.dist-info/RECORD
