Metadata-Version: 2.1
Name: quickstart_django
Version: 1.1
Summary: A small python package which will help you to quickly start your django project. It will create a django project with all the necessary files and folders in just single command.
Project-URL: Homepage, https://github.com/jaythorat/quickstart_django
Project-URL: Bug Tracker, https://github.com/jaythorat/quickstart_django/issues
Author-email: Jay Thorat <j.thorat10@gmail.com>
License-File: LICENCE
Classifier: License :: OSI Approved :: MIT License
Classifier: Operating System :: OS Independent
Classifier: Programming Language :: Python :: 3
Requires-Python: >=3.10
